[
  {
    "userId": 1,
    "tournaments": [
      {
        "1": [
          {
            "matchId": 1,
            "winner_id": "2",
            "last_vote": [
              {
                "day": 28,
                "hours": 0,
                "mins": 40
              }
            ]
          }
        ]
      }
    ]
  },
  {
    "userId": 1,
    "tournaments": [
      {
        "1": [
          {
            "matchId": 2,
            "winner_id": "14",
            "last_vote": [
              {
                "day": 28,
                "hours": 0,
                "mins": 49
              }
            ]
          }
        ]
      }
    ]
  },
  {
    "userId": 1,
    "tournaments": [
      {
        "1": [
          {
            "matchId": 1,
            "winner_id": "2",
            "last_vote": [
              {
                "day": 28,
                "hours": 0,
                "mins": 55
              }
            ]
          }
        ]
      }
    ]
  },
  {
    "userId": 1,
    "tournaments": [
      {
        "1": [
          {
            "matchId": 3,
            "winner_id": "6",
            "last_vote": [
              {
                "day": 28,
                "hours": 1,
                "mins": 2
              }
            ]
          }
        ]
      }
    ]
  },
  {
    "userId": 1,
    "tournaments": [
      {
        "1": [
          {
            "matchId": 4,
            "winner_id": "10",
            "last_vote": [
              {
                "day": 28,
                "hours": 1,
                "mins": 5
              }
            ]
          }
        ]
      }
    ]
  },
  {
    "userId": 1,
    "tournaments": [
      {
        "1": [
          {
            "matchId": 5,
            "winner_id": "9",
            "last_vote": [
              {
                "day": 28,
                "hours": 1,
                "mins": 7
              }
            ]
          }
        ]
      }
    ]
  },
  {
    "userId": 1,
    "tournaments": [
      {
        "1": [
          {
            "matchId": 6,
            "winner_id": "13",
            "last_vote": [
              {
                "day": 28,
                "hours": 1,
                "mins": 10
              }
            ]
          }
        ]
      }
    ]
  },
  {
    "userId": 1,
    "tournaments": [
      {
        "1": [
          {
            "matchId": 1,
            "winner_id": "1",
            "last_vote": [
              {
                "day": 28,
                "hours": 1,
                "mins": 18
              }
            ]
          }
        ]
      }
    ]
  },
  {
    "userId": 1,
    "tournaments": [
      {
        "1": [
          {
            "matchId": 2,
            "winner_id": "3",
            "last_vote": [
              {
                "day": 28,
                "hours": 1,
                "mins": 20
              }
            ]
          }
        ]
      }
    ]
  },
  {
    "userId": 1,
    "tournaments": [
      {
        "1": [
          {
            "matchId": 3,
            "winner_id": "6",
            "last_vote": [
              {
                "day": 28,
                "hours": 1,
                "mins": 21
              }
            ]
          }
        ]
      }
    ]
  },
  {
    "userId": 1,
    "tournaments": [
      {
        "1": [
          {
            "matchId": 4,
            "winner_id": "14",
            "last_vote": [
              {
                "day": 28,
                "hours": 1,
                "mins": 23
              }
            ]
          }
        ]
      }
    ]
  },
  {
    "userId": 1,
    "tournaments": [
      {
        "1": [
          {
            "matchId": 2,
            "winner_id": "3",
            "last_vote": [
              {
                "day": 28,
                "hours": 1,
                "mins": 39
              }
            ]
          }
        ]
      }
    ]
  }
]